ruphrase/__init__.py
ruphrase/functions.py
ruphrase-0.0.5.dist-info/LICENSE
ruphrase-0.0.5.dist-info/METADATA
ruphrase-0.0.5.dist-info/WHEEL
ruphrase-0.0.5.dist-info/top_level.txt
ruphrase-0.0.5.dist-info/RECORD
