Metadata-Version: 2.1
Name: ruphrase
Version: 0.0.5
Summary: Build the correct turn of phrase in Russian
Home-page: https://github.com/nigani/ruphrase
Author: nigani
Author-email: nigani@internet.ru
License: MIT License
Platform: UNKNOWN
License-File: LICENSE
